AUTHORS
ChangeLog
LICENSE.rst
MANIFEST.in
README.rst
setup.cfg
setup.py
tox.ini
jingtrang/__init__.py
jingtrang/jing.jar
jingtrang/trang.jar
jingtrang.egg-info/PKG-INFO
jingtrang.egg-info/SOURCES.txt
jingtrang.egg-info/dependency_links.txt
jingtrang.egg-info/entry_points.txt
jingtrang.egg-info/not-zip-safe
jingtrang.egg-info/pbr.json
jingtrang.egg-info/top_level.txt
tests/test_it.py
tests/dataset-rdstmc/messages/live_2014-07-31T13-36-52Z.xml
tests/dataset-rdstmc/messages/live_2014-07-31T13-37-02Z.xml
tests/dataset-rdstmc/messages/live_2014-07-31T13-37-04Z.xml
tests/dataset-rdstmc/schemas/information.rnc
tests/dataset-rdstmc/schemas/journal.rnc
tests/dataset-rdstmc/schemas/message.rnc
tests/dataset-rdstmc/schemas/rdsquality.rnc
tests/dataset-rdstmc/schemas/root.rnc
tests/dataset-rdstmc/schemas/snapshot.rnc
tests/dataset-rdstmc/schemas/types.rnc
tests/dataset-rntutor/messages/valid.xml
tests/dataset-rntutor/schemas/root.rnc
tests/dataset-wiki/messages/book.xml
tests/dataset-wiki/schemas/root.rnc