Metadata-Version: 1.1
Name: jingtrang
Version: 0.1.1
Summary: Wrapping jing and trang RELAX NG tools into Python script
Home-page: http://bitbucket.org/tamtamresearch/jingtrang
Author: Jan Vlcinsky
Author-email: jan.vlcinsky@tamtamresearch.com
License: UNKNOWN
Platform: UNKNOWN
Classifier: Development Status :: 4 - Beta
Classifier: Environment :: Console
Classifier: Intended Audience :: Developers
Classifier: Intended Audience :: Information Technology
Classifier: License :: OSI Approved :: MIT License
Classifier: Operating System :: OS Independent
Classifier: Programming Language :: Java
Classifier: Programming Language :: Python :: 2.6
Classifier: Programming Language :: Python :: 2.7
Classifier: Programming Language :: Python :: 3.4
Classifier: Programming Language :: Python :: 3.5
Classifier: Topic :: Software Development :: Quality Assurance
Classifier: Topic :: Software Development :: Testing
Classifier: Topic :: Utilities
